{
    "850f305d-14db-4c75-b547-79470a557ea3-598679": {
        "articles": {
            "resultCount": 11,
            "results": [
                {
                    "body": "WASHINGTON: The Pentagon said on Friday the transfer of heavy caliber multiple launch rocket systems from Russia to Ukrainian separatists appeared to be imminent, with the arms close enough to the border they could be handed over \"potentially today.\"\n\n\"We have indications that the Russians intend to supply heavier and more sophisticated multiple launch rocket systems in the very near future,\" said Army Colonel Steve Warren, a Pentagon spokesman, adding that the weapons were in the over-200mm range.\n\nWarren indicated the weapons had been seen getting closer to the border and the Pentagon believed a transfer was imminent and \"potentially today.\"\n\n\"We believe that they are able to transfer this equipment at any time, at any moment,\" he said.",
                    "date": "2014-07-25",
                    "eventUri": "1069645",
                    "id": "16160396",
                    "isDuplicate": false,
                    "lang": "eng",
                    "sim": 0.8665,
                    "source": {
                        "title": "Economic Times",
                        "uri": "economictimes.indiatimes.com"
                    },
                    "time": "16:52:00",
                    "title": "'Russia transfer of rocket system to Ukraine rebels imminent'",
                    "uri": "199698009",
                    "url": "http://economictimes.indiatimes.com/news/international/world-news/russia-transfer-of-rocket-system-to-ukraine-rebels-imminent-pentagon/articleshow/39000090.cms",
                    "wgt": 1
                },
                {
                    "body": "WASHINGTON -- The Pentagon said on Friday that the transfer of heavy caliber multiple launch rocket systems from Russia to Ukrainian separatists appeared to be imminent, with the arms close enough to the border they could be handed over \"potentially today.\"\n\n\"We have indications that the Russians intend to supply heavier and more sophisticated multiple launch rocket systems in the very near future,\" said Army Colonel Steve Warren, a Pentagon spokesman, adding that the weapons were in the over-200mm range.\n\nWarren indicated the weapons had been seen getting closer to the border and the Pentagon believed a transfer was imminent and \"potentially today.\"\n\n\"We believe that they are able to transfer this equipment at any time, at any moment,\" he said.\n\nSee also:",
                    "date": "2014-07-25",
                    "eventUri": "1069645",
                    "id": "16161513",
                    "isDuplicate": false,
                    "lang": "eng",
                    "sim": 0.8665,
                    "source": {
                        "title": "The Moscow Times",
                        "uri": "www.themoscowtimes.com"
                    },
                    "time": "17:11:00",
                    "title": "Pentagon Says Russia About to Give Rocket Launchers to Ukrainian Rebels",
                    "uri": "199701201",
                    "url": "http://www.themoscowtimes.com/article/504098.html",
                    "wgt": 1
                },
                {
                    "body": "WASHINGTON, July 25 (Reuters) - The Pentagon said on Friday the transfer of heavy caliber multiple launch rocket systems from Russia to Ukrainian separatists appeared to be imminent, with the arms close enough to the border they could be handed over \"potentially today.\"\n\n\"We have indications that the Russians intend to supply heavier and more sophisticated multiple launch rocket systems in the very near future,\" said Army Colonel Steve Warren, a Pentagon spokesman, adding that the weapons were in the over-200mm range.\n\nWarren indicated the weapons had been seen getting closer to the border and the Pentagon believed a transfer was imminent and \"potentially today.\"",
                    "date": "2014-07-25",
                    "eventUri": "1069645",
                    "id": "16164469",
                    "isDuplicate": false,
                    "lang": "eng",
                    "sim": 0.8658,
                    "source": {
                        "title": "Reuters",
                        "uri": "www.reuters.com"
                    },
                    "time": "17:52:00",
                    "title": "Russia transfer of rocket system to Ukraine rebels imminent- Pentagon - Reuters",
                    "uri": "199709587",
                    "url": "http://www.reuters.com/article/2014/07/25/ukraine-crisis-rockets-usa-idUSL2N0Q01CS20140725",
                    "wgt": 1
                },
                {
                    "body": "WASHINGTON - The Pentagon said on Friday the transfer of heavy-caliber multiple-launch rocket systems from Russia to Ukrainian separatists appeared to be imminent with the arms close enough to the border they could be handed over \"potentially today.\"\n\n\"We have indications that the Russians intend to supply heavier and more sophisticated multiple-launch rocket systems in the very near future,\" said Army Colonel Steve Warren, a Pentagon spokesman, adding that the weapons were in the over-200mm range.\n\nWarren indicated the weapons had been seen getting closer to the border and the Pentagon believed a transfer was imminent and could happen \"potentially today.\"\n\n\"We believe that they are able to transfer this equipment at any time, at any moment,\" he said.\n\nWarren said it was unclear whether Russian operators of the rocket launchers might cross the border as well, but he said there have been indications of Russian operators of other systems going over.\n\nA multiple-launch rocket system is a wheeled or tracked vehicle mounted with multiple tubes capable of firing a half dozen or more guided or unguided rockets in quick succession at targets scores of miles (km) away. The rockets are generally 100mm to 300mm, with those over 200mm in the heavier-caliber category.\n\n\"We're very concerned with the quantity and the capability of weapons flowing from Russia into the Ukrainian separatists' hands,\" Warren said.\n\n\"There has been a continuous flow over the last several weeks of weapons and equipment from Russia to Ukraine,\" he said, noting that the \"most egregious example\" was a column of more than 100 vehicles crossing the border.\n\nThe Pentagon's assessment that a transfer of heavy weaponry was imminent came as Russian authorities accused Ukraine of firing a volley of mortar rounds across the frontier into Russia on Friday while a group of investigators was in the area assessing reports of cross-border shooting.\n\nA Russian security official said up to 40 mortar bombs fired by Ukrainian forces fell in the Russian province of Rostov near the border where Ukrainian government forces are fighting pro-Russian separatists. There were no reports of injuries.\n\nWarren also said the United States continued to see Russian artillery on Russian soil firing on Ukrainian military positions inside Ukraine, a practice that has been going on for several days now.\n\nHe said he had no information about Ukrainians firing across the border into Russia.\n\nWarren said the Pentagon continued to see a \"continuous slow and steady buildup\" of Russian forces along the border. He said the number was still in the 10,000- to 12,000-range, but was now \"towards the high side\" of that range.\n\nOthers officials estimated the size of the Russian force had grown larger. U.S. Ambassador to NATO Douglas Lute told a security forum in Aspen, Colorado, there were now some 15,000 Russian troops amassed along the Ukraine border.\n\nWarren said the growing size of the Russian force was \"very concerning to us.\"\n\n\"We've repeatedly called on the Russians to withdraw force from the border and to help de-escalate,\" he said.\n\nSee also:",
                    "date": "2014-07-25",
                    "eventUri": "1069645",
                    "id": "16167604",
                    "isDuplicate": false,
                    "lang": "eng",
                    "sim": 0.8487,
                    "source": {
                        "title": "The Moscow Times",
                        "uri": "www.themoscowtimes.com"
                    },
                    "time": "18:59:00",
                    "title": "Pentagon Says Russia About to Give Rocket Launchers to Ukrainian Rebels",
                    "uri": "199717830",
                    "url": "http://www.themoscowtimes.com/article/504098.html?utm_source=feedburner&utm_medium=feed&utm_campaign=Feed%253A%2Bthemoscowtimes%252FRUXi%2B%2528The%2BMoscow%2BTimes%2529&utm_content=FeedBurner%2Buser%2Bview",
                    "wgt": 1
                },
                {
                    "body": "Washington - The Pentagon said on Friday the transfer of heavy calibre multiple launch rocket systems from Russia to Ukrainian separatists appeared to be imminent, with the arms close enough to the border they could be handed over \"potentially today\".\n\n\"We have indications that the Russians intend to supply heavier and more sophisticated multiple launch rocket systems in the very near future,\" said Army Colonel Steve Warren, a Pentagon spokesperson, adding that the weapons were in the over-200mm range.\n\nWarren indicated the weapons had been seen getting closer to the border and the Pentagon believed a transfer was imminent and \"potentially today.\"\n\n\"We believe that they are able to transfer this equipment at any time, at any moment,\" he said.",
                    "date": "2014-07-26",
                    "eventUri": "1069645",
                    "id": "16181936",
                    "isDuplicate": false,
                    "lang": "eng",
                    "sim": 0.8362,
                    "source": {
                        "title": "News24",
                        "uri": "www.news24.com"
                    },
                    "time": "00:07:00",
                    "title": "News24.com | Russia transfering rocket system to Ukraine rebels",
                    "uri": "199758499",
                    "url": "http://www.news24.com/World/News/Russia-transfering-rocket-system-to-Ukraine-rebels-20140725",
                    "wgt": 1
                },
                {
                    "body": "\"We have indications that the Russians intend to supply heavier and more sophisticated multiple-launch rocket systems in the very near future,\" said Army Colonel Steve Warren, a Pentagon spokesman, adding that the weapons were in the over-200mm range.\n\nWarren indicated the weapons had been seen getting closer to the border and the Pentagon believed a transfer was imminent and could happen \"potentially today.\"\n\n\"We believe that they are able to transfer this equipment at any time, at any moment,\" he said.\n\nWarren said it was unclear whether Russian operators of the rocket launchers might cross the border as well but he said there been indications of Russian operators of other systems going over.\n\nA multiple-launch rocket system is a wheeled or tracked vehicle mounted with multiple tubes capable of firing a half dozen or more guided or unguided rockets in quick succession at targets scores of miles (km) away. The rockets are generally 100mm to 300mm, with those over 200mm in the heavier-caliber category.\n\n\"We're very concerned with the quantity and the capability of weapons flowing from Russia into the Ukrainian separatists' hands,\" Warren said.\n\n\"There has been a continuous flow over the last several weeks of weapons and equipment from Russia to Ukraine,\" he said, noting that the \"most egregious example\" was a column of more than 100 vehicles crossing the border.\n\nThe Pentagon's assessment that a transfer of heavy weaponry was imminent came as Russian authorities accused Ukraine of firing a volley of mortar rounds across the frontier into Russia on Friday while a group of investigators was in the area assessing reports of cross-border shooting.\n\nA Russian security official said up to 40 mortar bombs fired by Ukrainian forces fell in the Russian province of Rostov near the border where Ukrainian government forces are fighting pro-Russian separatists. There were no reports of injuries.\n\nWarren also said the United States continued to see Russian artillery on Russian soil firing on Ukrainian military positions inside Ukraine, a practice that has been going on for several days now.\n\nHe said he had no information about Ukrainians firing across the border into Russia.\n\nWarren said the Pentagon continued to see a \"continuous slow and steady buildup\" of Russian forces along the border. He said the number was still in the 10,000- to 12,000-range, but was now \"towards the high side\" of that range.\n\nOthers officials estimated the size of the Russian force had grown larger. U.S. Ambassador to NATO Douglas Lute told a security forum in Aspen, Colorado, there were now some 15,000 Russian troops amassed along the Ukraine border.\n\nWarren said the growing size of the Russian force was \"very concerning to us.\"\n\n\"We've repeatedly called on the Russians to withdraw force from the border and to help de-escalate,\" he said.\n\n(Additional reporting by Phil Stewart in Aspen, Colorado; Editing by Bill Trott)",
                    "date": "2014-07-25",
                    "eventUri": "1069645",
                    "id": "16264174",
                    "isDuplicate": false,
                    "lang": "eng",
                    "sim": 0.7902,
                    "source": {
                        "title": "Reuters India",
                        "uri": "in.reuters.com"
                    },
                    "time": "10:00:00",
                    "title": "Russia transfer of rocket system to Ukraine rebels imminent - Pentagon",
                    "uri": "200057325",
                    "url": "http://in.reuters.com/article/2014/07/25/ukraine-crisis-rockets-usa-idINKBN0FU21320140725",
                    "wgt": 1
                },
                {
                    "body": "U.S. intelligence indicates that Russia plans to soon provide heavier and more sophisticated weaponry to Ukrainian separatists, a Pentagon spokesman said on Friday.\n\n\"We have indications that the Russians intend to supply heavier and more sophisticated multiple launch rocket systems in the very near future,\" said Army Colonel Steve Warren, a Pentagon spokesman, adding that the weapons were in the over-200mm range.\n\nRead More Ukraine: What's the next big disruption?\n\nWarren indicated the weapons had been seen getting closer to the border and the Pentagon believed a transfer was imminent and \"potentially today.\"\n\n\"We believe that they are able to transfer this equipment at any time, at any moment,\" he said.\n\nWarren said that the U.S. has seen a consistent flow of weaponry into Ukraine from Russia for several weeks.\n\nRead More Ukraine rebel fighters had BUK missiles: Leader\n\nClick here for the latest on the markets.\n\n-- By Reuters with CNBC",
                    "date": "2014-07-25",
                    "eventUri": "1069645",
                    "id": "16160417",
                    "isDuplicate": false,
                    "lang": "eng",
                    "sim": 0.7544,
                    "source": {
                        "title": "CNBC",
                        "uri": "www.cnbc.com"
                    },
                    "time": "16:51:00",
                    "title": "Pentagon: Russian missiles to rebels",
                    "uri": "199697795",
                    "url": "http://www.cnbc.com/id/101860795",
                    "wgt": 1
                },
                {
                    "body": "WASHINGTON -- The Pentagon says the movement of Russian heavy caliber artillery systems across the border into Ukraine is \"imminent\", escalating the military action there.\n\nCol. Steve Warren, citing U.S. intelligence, says the U.S. has seen the systems moving closer to the border and they could be put into the hands of Russian-backed separatists as soon as Friday. He says he doesn't have an exact timeline.\n\nWarren also says Russia continues to fire artillery across the border into Ukraine but the U.S. has seen no indications of Ukraine firing back into Russia. He says the number of Russian troops along the border continues to slowly but steadily increase. Close to 12,000 are there now.",
                    "date": "2014-07-25",
                    "eventUri": "1069645",
                    "id": "16160045",
                    "isDuplicate": false,
                    "lang": "eng",
                    "sim": 0.7453,
                    "source": {
                        "title": "miamiherald",
                        "uri": "www.miamiherald.com"
                    },
                    "time": "16:46:00",
                    "title": "Bigger Russian artillery moving into Ukraine soon",
                    "uri": "199697014",
                    "url": "http://www.miamiherald.com/2014/07/25/4254614/bigger-russian-artillery-moving.html",
                    "wgt": 1
                },
                {
                    "body": "WASHINGTON - The Pentagon says the movement of Russian heavy caliber artillery systems across the border into Ukraine is \"imminent\", escalating the military action there.\n\nCol. Steve Warren, citing U.S. intelligence, says the U.S. has seen the systems moving closer to the border and they could be put into the hands of Russian-backed separatists as soon as Friday. He says he doesn't have an exact timeline.\n\nADVERTISEMENT\n\nADVERTISEMENT\n\nWarren also says Russia continues to fire artillery across the border into Ukraine but the U.S. has seen no indications of Ukraine firing back into Russia. He says the number of Russian troops along the border continues to slowly but steadily increase. Close to 12,000 are there now.",
                    "date": "2014-07-25",
                    "eventUri": "1069645",
                    "id": "16159611",
                    "isDuplicate": false,
                    "lang": "eng",
                    "sim": 0.7197,
                    "source": {
                        "title": "Fox News",
                        "uri": "www.foxnews.com"
                    },
                    "time": "16:40:00",
                    "title": "Pentagon: Imminent movement of Russian heavy artillery across border into Ukraine",
                    "uri": "199696006",
                    "url": "http://www.foxnews.com/us/2014/07/25/pentagon-imminent-movement-russian-heavy-artillery-across-border-into-ukraine/?utm_source=feedburner&utm_medium=feed&utm_campaign=Feed%253A%2Bfoxnews%252Fnational%2B%2528Internal%2B-%2BUS%2BLatest%2B-%2BText%2529",
                    "wgt": 1
                },
                {
                    "body": "WASHINGTON (AP) -- The Pentagon says the movement of Russian heavy caliber artillery systems across the border into Ukraine is \"imminent\", escalating the military action there.\n\nCol. Steve Warren, citing U.S. intelligence, says the U.S. has seen the systems moving closer to the border and they could be put into the hands of Russian-backed separatists as soon as Friday. He says he doesn't have an exact timeline.\n\nWarren also says Russia continues to fire artillery across the border into Ukraine but the U.S. has seen no indications of Ukraine firing back into Russia. He says the number of Russian troops along the border continues to slowly but steadily increase. Close to 12,000 are there now.\n\nCopyright 2014 The Associated Press. All rights reserved. This material may not be published, broadcast, rewritten or redistributed.",
                    "date": "2014-07-25",
                    "eventUri": "1069645",
                    "id": "16159467",
                    "isDuplicate": false,
                    "lang": "eng",
                    "sim": 0.7189,
                    "source": {
                        "title": "US News & World Report",
                        "uri": "www.usnews.com"
                    },
                    "time": "16:37:00",
                    "title": "Bigger Russian artillery moving into Ukraine soon",
                    "uri": "199695543",
                    "url": "http://www.usnews.com/news/politics/articles/2014/07/25/bigger-russian-artillery-moving-into-ukraine-soon",
                    "wgt": 1
                },
                {
                    "body": "The Pentagon said Friday that Russia was moving troops and adding heavier artillery near its border with Ukraine where separatists are battling government forces, the latest escalation of Moscow's involvement in the conflict.\n\nCol. Steve Warren, a Pentagon spokesman, said that U.S. intelligence reports showed Russia was planning to give the separatists up to a dozen 200-millimeter rocket launchers, an artillery system that is more powerful than the rebels have received before.\n\n\"We have indications that the Russians intend to supply heavier and more sophisticated multiple-launch rocket systems in the very near future,\" Warren said, adding that the arms had been moved near Russia's southwest border with Ukraine and that their movement across the border appeared \"imminent.\"\n\nU.S. officials said Russia was stepping up its direct role in the conflict after gains by government forces, who claimed to have retaken the city of Lysychansk in eastern Ukraine from Moscow-backed separatists. After the downing of a Malaysian jetliner over Ukraine last week, President Obama had called for a cease-fire in the conflict and for Moscow to de-escalate its role.\n\nInstead, \"for the last several days, Russian forces using Russian artillery from Russian soil have conducted attacks against Ukrainian military positions,\" Warren said.\n\nThe Russians also have increased their troop presence in the border region to about 12,000, he said.\n\n\"This is unquestionably an escalation from a military perspective, and it flies in the face of everything Russians have said up until now,\" he said.\n\nRussia on Friday called the U.S. accusations of Moscow's involvement in the Ukrainian conflict a \"smear campaign.\"\n\nA U.S. military official, who requested anonymity to discuss intelligence reports, said the rocket salvos appeared aimed at preventing Ukrainian forces from regaining control of the border region southeast of the city of Donetsk.\n\nHe said that U.S. intelligence had seen nearly 100 shell craters in one area, indicating that location had been struck by a heavy barrage.\n\nWarren said there had been several instances of rocket fire from Russia.\n\nThe Russian launchers that have been moved to the border fire multiple surface-to-surface missiles in rapid salvos and are considered less accurate than the SA-11 surface-to-air system believed responsible for downing the Malaysia Airlines jet.\n\n\"They're not precision munitions,\" Warren said, \"and unquestionably there is an increased risk of civilian casualties.\"\n\nWarren said that Russia has previously provided rebels with smaller rockets and other weapons but that the transfer of 200-millimeter rockets would involve the heaviest artillery so far.",
                    "date": "2014-07-25",
                    "eventUri": "1069645",
                    "id": "16181222",
                    "isDuplicate": false,
                    "lang": "eng",
                    "sim": 0.653,
                    "source": {
                        "title": "latimes.com",
                        "uri": "www.latimes.com"
                    },
                    "time": "23:22:00",
                    "title": "US says Russia is moving bigger rocket launchers to Ukraine border - Los Angeles Times",
                    "uri": "199756236",
                    "url": "http://www.latimes.com/world/europe/la-fg-rockets-ukraine-20140725-story.html",
                    "wgt": 1
                }
            ]
        },
        "info": {
            "articleCount": 11,
            "averageDate": "2014-07-25",
            "avgCos": 0.557,
            "categories": [],
            "customDate": false,
            "customLocation": false,
            "eventUri": "1069645",
            "extractedDate": "",
            "extractedDateEnd": "",
            "id": "1069645",
            "lang": "eng",
            "storyDate": "2014-07-25",
            "storyDateEnd": "",
            "uri": "850f305d-14db-4c75-b547-79470a557ea3-598679",
            "variance": 0.1897
        }
    },
    "e7e700df-6a06-44ea-a4f3-f736278fc36b-222287": {
        "articles": {
            "resultCount": 8,
            "results": [
                {
                    "body": "La portavoz del Departamento de Estado asegur\u00f3 que EE.UU. tiene \"evidencias de que Rusia est\u00e1 disparando piezas de artiller\u00eda desde Rusia a posiciones ucranianas\".\n\nEstados Unidos asegur\u00f3 hoy que tiene pruebas de que Rusia ha estado disparando rondas de artiller\u00eda desde su territorio contra posiciones de las Fuerzas Armadas ucranianas para ayudar a los rebeldes prorrusos.\n\nLa portavoz del Departamento de Estado, Marie Harf, asegur\u00f3 que Estados Unidos tiene \"evidencias de que Rusia est\u00e1 disparando piezas de artiller\u00eda desde Rusia para atacar posiciones militares ucranianas\".\n\nAdem\u00e1s, la portavoz de Estado asegur\u00f3 que Rusia est\u00e1 intentando enviar a las milicias rebeldes \"varios tipos de lanzaderas de cohetes m\u00e1s poderosas y fuego m\u00e1s pesado\", algo en lo que coinciden los analistas del Pent\u00e1gono.\n\nSeg\u00fan fuentes del Departamento de Defensa, Rusia tambi\u00e9n ha provisto a los rebeldes de las regiones del este ucraniano de un centenar de veh\u00edculos militares, incluidos tanques, lo que demostrar\u00eda la implicaci\u00f3n activa de Rusia en el conflicto ucraniano.\n\nEstados Unidos sigue considerando que Rusia mantiene entre 10.000 y 12.000 tropas bien equipadas y listas para el combate cerca de su frontera con Ucrania.\n\nLa tensi\u00f3n entre EE.UU. y Rusia a prop\u00f3sito de la crisis separatista en Ucrania se ha incrementado con el m\u00e1s que probable derribo del avi\u00f3n de pasajeros de Malaysia Airlines MH17, en el que fallecieron 298 personas.\n\nLos servicios de inteligencia estadounidenses dan por hecho que un misil de origen sovi\u00e9tico del tipo BUK SA-11 fue el responsable del derribo en pleno vuelo del avi\u00f3n y probablemente fue operado por separatistas que cometieron un error al pensar que la aeronave era militar.",
                    "date": "2014-07-24",
                    "eventUri": "1069645",
                    "id": "16099696",
                    "isDuplicate": false,
                    "lang": "spa",
                    "sim": 0.8837,
                    "source": {
                        "title": "elsolonline.com",
                        "uri": "elsolonline.com"
                    },
                    "time": "20:42:00",
                    "title": "EE.UU. acusa a Rusia de bombardear posiciones ucranianas desde su territorio",
                    "uri": "199520405",
                    "url": "http://elsolonline.com/noticias/ver/1407/209462/ee-uu-acusa-a-rusia-de-bombardear-posiciones-ucranianas-desde-su-territorio",
                    "wgt": 1
                },
                {
                    "body": "Estados Unidos asegur\u00f3 que tiene pruebas de que Rusia ha estado disparando rondas de artiller\u00eda desde su territorio contra posiciones de las Fuerzas Armadas ucranianas para ayudar a los rebeldes prorrusos.\n\nLa portavoz del Departamento de Estado, Marie Harf, asegur\u00f3 que Estados Unidos tiene \"evidencias de que Rusia est\u00e1 disparando piezas de artiller\u00eda desde Rusia para atacar posiciones militares ucranianas\".\n\nAdem\u00e1s, la portavoz de Estado asegur\u00f3 que Rusia est\u00e1 intentando enviar a las milicias rebeldes \"varios tipos de lanzaderas de cohetes m\u00e1s poderosas y fuego m\u00e1s pesado\", algo en lo que coinciden los analistas del Pent\u00e1gono.\n\nSeg\u00fan fuentes del Departamento de Defensa, Rusia tambi\u00e9n ha provisto a los rebeldes de las regiones del este ucraniano de un centenar de veh\u00edculos militares, incluidos tanques, lo que demostrar\u00eda la implicaci\u00f3n activa de Rusia en el conflicto ucraniano.\n\nEstados Unidos sigue considerando que Rusia mantiene entre 10.000 y 12.000 tropas bien equipadas y listas para el combate cerca de su frontera con Ucrania.\n\nLa tensi\u00f3n entre EE.UU. y Rusia a prop\u00f3sito de la crisis separatista en Ucrania se ha incrementado con el m\u00e1s que probable derribo del avi\u00f3n de pasajeros de Malaysia Airlines MH17, en el que fallecieron 298 personas.\n\nLos servicios de inteligencia estadounidenses dan por hecho que un misil de origen sovi\u00e9tico del tipo BUK SA-11 fue el responsable del derribo en pleno vuelo del avi\u00f3n y probablemente fue operado por separatistas que cometieron un error al pensar que la aeronave era militar",
                    "date": "2014-07-24",
                    "eventUri": "1069645",
                    "id": "16107236",
                    "isDuplicate": false,
                    "lang": "spa",
                    "sim": 0.8754,
                    "source": {
                        "title": "Cooperativa",
                        "uri": "www.cooperativa.cl"
                    },
                    "time": "22:53:00",
                    "title": "EE.UU. asegur\u00f3 tener pruebas de bombardeos rusos contra posiciones ucranianas - Cooperativa.cl",
                    "uri": "199540234",
                    "url": "http://www.cooperativa.cl/noticias/mundo/ee-uu-/relaciones-exteriores/ee-uu-aseguro-tener-pruebas-de-bombardeos-rusos-contra-posiciones-ucranianas/2014-07-24/183642.html",
                    "wgt": 1
                },
                {
                    "body": "Departamento de Estado tiene pruebas que incriminan a gobierno ruso.\n\nEstados Unidos asegur\u00f3 que tiene pruebas de que Rusia ha estado disparando rondas de artiller\u00eda desde su territorio contra posiciones de las Fuerzas Armadas ucranianas para ayudar a los rebeldes prorrusos.\n\nLa portavoz del Departamento de Estado, Marie Harf, asegur\u00f3 que EEUU tiene \"evidencias de que Rusia est\u00e1 disparando piezas de artiller\u00eda desde Rusia para atacar posiciones militares ucranianas\".\n\nAdem\u00e1s, la portavoz de Estado asegur\u00f3 que Rusia est\u00e1 intentando enviar a las milicias rebeldes \"varios tipos de lanzaderas de cohetes m\u00e1s poderosas y fuego m\u00e1s pesado\", algo en lo que coinciden los analistas del Pent\u00e1gono.\n\nSeg\u00fan fuentes del Departamento de Defensa, Rusia tambi\u00e9n ha provisto a los rebeldes de las regiones del este ucraniano de un centenar de veh\u00edculos militares, incluidos tanques, lo que demostrar\u00eda la implicaci\u00f3n activa de Rusia en el conflicto ucraniano.\n\nEEUU sigue considerando que Rusia mantiene entre 10.000 y 12.000 tropas bien equipadas y listas para el combate cerca de su frontera con Ucrania.\n\nLa tensi\u00f3n entre EEUU y Rusia a prop\u00f3sito de la crisis separatista en Ucrania, se ha incrementado con el probable derribo del avi\u00f3n de pasajeros de Malaysia Airlines MH17. Pa\u00edses de la Uni\u00f3n Europea, preparan sanciones econ\u00f3micas contra Rusia por sus papel en la crisis ucraniana, en acceso a mercados de capitales, defensa y uso dual (civil y militar) de bienes y tecnolog\u00eda sensible especialmente en el sector de la energ\u00eda.",
                    "date": "2014-07-25",
                    "eventUri": "1069645",
                    "id": "16128030",
                    "isDuplicate": false,
                    "lang": "spa",
                    "sim": 0.8493,
                    "source": {
                        "title": "www.elheraldo.co",
                        "uri": "www.elheraldo.co"
                    },
                    "time": "07:22:00",
                    "title": "Rusia bombardea a Ucrania: EEUU - El Heraldo (Colombia)",
                    "uri": "199603575",
                    "url": "http://www.elheraldo.co/internacional/rusia-bombardea-ucrania-eeuu-160529",
                    "wgt": 1
                },
                {
                    "body": "El presidente de EEUU, Barack Obama, y el primer ministro holand\u00e9s, Mark Rutte, lamentaron este jueves el que, seg\u00fan \"todas las pruebas\", Rusia siga armando a los rebeldes en Ucrania y consideraron necesario imponer m\u00e1s sanciones a la Federaci\u00f3n Rusa .\n\nObama mencion\u00f3, durante una conversaci\u00f3n telef\u00f3nica con Rutte, las \"conmovedoras im\u00e1genes\" de la llegada el mi\u00e9rcoles a Holanda de los primeros restos mortales de las v\u00edctimas del avi\u00f3n de Malaysian Airlines siniestrado en el este de Ucrania y ofreci\u00f3 nuevamente sus condolencias al l\u00edder holand\u00e9s.\n\nDe los 298 pasajeros a bordo del avi\u00f3n malayo, 193 eran holandeses.\n\nObama y Rutte concordaron en que \"en lugar de reducir la tensi\u00f3n, todas las pruebas indican que Rusia todav\u00eda est\u00e1 armando y ofreciendo apoyo a los separatistas que contin\u00faan involucrados en actos letales de agresi\u00f3n contra las fuerzas armadas ucranianas\".\n\nAmbos l\u00edderes estuvieron de acuerdo en que \"no se puede permitir que Rusia desestabilice la situaci\u00f3n en Ucrania sin incurrir en costes\" adicionales.\n\n\"La comunidad internacional deber\u00e1 aplicar sanciones adicionales a Mosc\u00fa\", coincidieron Obama y Rutte, seg\u00fan el comunicado de la residencia oficial estadounidense.\n\nEstados Unidos dijo este jueves tener pruebas de que Rusia ha estado disparando rondas de artiller\u00eda desde su territorio contra posiciones de las Fuerzas Armadas ucranianas para asistir a los rebeldes prorrusos.\n\nAdem\u00e1s, el Departamento de Estado asegur\u00f3 que Rusia est\u00e1 intentando enviar a las milicias rebeldes \"varios tipos de lanzaderas de cohetes m\u00e1s poderosas y fuego m\u00e1s pesado\", algo en lo que coinciden los analistas del Pent\u00e1gono.\n\nSeg\u00fan fuentes del Departamento de Defensa, Rusia tambi\u00e9n ha provisto a los rebeldes de las regiones del este ucraniano con un centenar de veh\u00edculos militares, incluidos tanques, lo que demostrar\u00eda la implicaci\u00f3n activa de Mosc\u00fa en el conflicto.\n\nEstados Unidos sigue considerando que Rusia mantiene entre 10.000 y 12.000 tropas bien equipadas y listas para el combate cerca de su frontera con Ucrania.\n\nLa inteligencia estadounidense da por hecho que un misil de origen sovi\u00e9tico del tipo BUK SA-11 fue el responsable del derribo en pleno vuelo del avi\u00f3n y probablemente fue operado por separatistas que habr\u00edan cometido un error al pensar que la aeronave era militar.",
                    "date": "2014-07-25",
                    "eventUri": "1069645",
                    "id": "16118346",
                    "isDuplicate": false,
                    "lang": "spa",
                    "sim": 0.737,
                    "source": {
                        "title": "www.rpp.com.pe",
                        "uri": "www.rpp.com.pe"
                    },
                    "time": "03:30:00",
                    "title": "EEUU y Holanda consideran necesarias sanciones adicionales a Rusia",
                    "uri": "199573240",
                    "url": "http://www.rpp.com.pe/2014-07-24-eeuu-y-holanda-consideran-necesarias-sanciones-adicionales-a-rusia-noticia_710852.html",
                    "wgt": 1
                },
                {
                    "body": "DONETSK, Ucrania (CNN) -- Los Estados Unidos, en coordinaci\u00f3n con sus aliados europeos, \"implementar\u00e1 medidas adicionales\" contra Rusia esta semana, seg\u00fan indic\u00f3 este lunes el viceasesor de Seguridad Nacional de la Casa Blanca, Tony Blinket.\n\nRepresentantes de los estados miembros de la Uni\u00f3n Europea se reunir\u00e1n este martes para considerar las propuestas, apunt\u00f3 el sitio web de la Uni\u00f3n Europea.\n\nLas nuevas propuestas incluyen sanciones en armas, bienes que pueden ser usados para prop\u00f3sitos civiles y militares, el accesos a los mercados de capital europeos y en la exportaci\u00f3n de tecnolog\u00eda energ\u00e9tica de Europa a Rusia.\n\nLa vocera del Departamento de Estado, Jen Psaki, dijo este lunes que lo que suceder\u00e1 despu\u00e9s depender\u00e1 de Rusia.\n\n\"Vemos un serio impacto de aquellas sanciones que hemos puesto en marcha hasta la fecha\", indic\u00f3.\n\n\"Los europeo quieren hacer m\u00e1s. Esperamos que hagan m\u00e1s\", dijo Psaki. \"As\u00ed que la pregunta para los rusos es: \u00bfse preocupan sobre su econom\u00eda y c\u00f3mo est\u00e1 impactando a su gente o van a negar el impacto que estas sanciones tienen?\"\n\nEl ministro del Exterior de Rusia, Sergey Lavrov dijo el lunes que el gobierno ruso no estaba feliz sobre las sanciones, pero que el pa\u00eds se sobrepondr\u00e1 de cualquier dificultad econ\u00f3mica y ser\u00e1 m\u00e1s independiente como resultado.\n\n\"No solo vemos el deseo de los socios europeos para castigar a Rusia\", se\u00f1al\u00f3.\n\nA m\u00e1s de una semana del accidente a\u00e9reo del avi\u00f3n de Malaysia Airlines en el este Ucrania, rebeldes prorrusos han impedido que investigadores internacionales accedan a la zona del siniestro.\n\nOficiales de Estados Unidos y Ucrania han se\u00f1alado que un sistema de misiles de fabricaci\u00f3n rusa fue usado para derribar al avi\u00f3n comercial, aunque Rusia y los rebeldes han refutado las acusaciones y culpado a los ucranianos del accidente.\n\nLas Naciones Unidas y otros pa\u00edses han llamado repetidamente al cese al fuego para permitir a los investigadores un ambiente de trabajo seguro en el lugar del accidente que el jefe de los derechos humanos de la ONU ha llamado la escena de un crimen de guerra.",
                    "date": "2014-07-28",
                    "eventUri": "1069645",
                    "id": "16321247",
                    "isDuplicate": false,
                    "lang": "spa",
                    "sim": 0.6074,
                    "source": {
                        "title": "mexico.cnn.com",
                        "uri": "mexico.cnn.com"
                    },
                    "time": "21:34:00",
                    "title": "EU y Europa impondr\u00e1n m\u00e1s sanciones a Rusia",
                    "uri": "200212679",
                    "url": "http://mexico.cnn.com/mundo/2014/07/28/eu-y-sus-aliados-europeos-implementaran-sanciones-adicionales-contra-rusia",
                    "wgt": 1
                },
                {
                    "body": "DONETSK, Ucrania (CNN) -- Estados Unidos inform\u00f3 este jueves que tiene pruebas de que Rusia est\u00e1 dispar\u00e1ndole a Ucrania.\n\n\"Tenemos nueva evidencia de que los rusos planean continuar la entrega de misiles m\u00e1s pesados y poderosos a las fuerzas separatistas en Ucrania y tenemos evidencia de que Rusia est\u00e1 utilizando su artiller\u00eda desde Rusia para atacar la posiciones militares ucranianas\", dijo la vocera del Departamento de Estado, Marie Harf.\n\nDos funcionarios estadounidenses informaron este jueves que las tropas rusas cerca de la frontera con Ucrania se han dividido en grupos m\u00e1s peque\u00f1os y se han movido m\u00e1s cerca a territorio ucraniano.\n\nUn periodista ucraniano trabajando como freelancer para CNN ha sido detenido por los rebeldes rusos.\n\nHombres armados de la autoproclamada Rep\u00fablica de la Gente de Donetsk atraparon a Anton Skiba afuera del hotel en el que se quedaba el martes en la ciudad de Donetsk, controlada por rebeldes.\n\nUn funcionario de la autoproclamada Rep\u00fablica de la Gente acus\u00f3 inicialmente a Skiba de \"terrorismo\" y de ofrecer premios econ\u00f3micos a quien mate rebeldes, seg\u00fan publicanos de la p\u00e1gina de Facebook del reportero.\n\nPoco despu\u00e9s, el funcionario retir\u00f3 la acusaci\u00f3n sobre las publicaciones en la red social y dijo que Skiba estaba siendo interrogado por tener m\u00faltiples identificaciones con varios nombres.\n\nEl mi\u00e9rcoles, otro funcionario de alto rango de los separatistas le dijo a CNN que Skiba admiti\u00f3 ser un \"agente ucraniano\".\n\nInicialmente, CNN opt\u00f3 por no reportar la detenci\u00f3n del reportero mientras intentaba asegurar su liberaci\u00f3n.\n\nLos cuerpos llegan a Holanda\n\nAviones que llevaban los restos de 74 personas arribaron este jueves en una base militar en Eindhoven. Unos 40 ata\u00fades de madera volaron el mi\u00e9rcoles y fueron recibidos por grupos de personas y tributos alrededor de Holanda.\n\nDe los ciudadanos de 10 pa\u00edses que murieron en el vuelo 17, la mayor\u00eda, 193, eran holandeses.\n\nLos rebeldes se adjudicaron la responsabilidad por derribar dos aviones militares ucranianos el mi\u00e9rcoles. Los rebeldes han negado responsabilidad en el derribamiento del vuelo 17, negando las acusaciones de funcionarios estadounidenses y ucranianos.",
                    "date": "2014-07-24",
                    "eventUri": "1069645",
                    "id": "16107703",
                    "isDuplicate": false,
                    "lang": "spa",
                    "sim": 0.5936,
                    "source": {
                        "title": "mexico.cnn.com",
                        "uri": "mexico.cnn.com"
                    },
                    "time": "23:04:00",
                    "title": "EU dice que Rusia est\u00e1 disparando a Ucrania",
                    "uri": "199541566",
                    "url": "http://mexico.cnn.com/mundo/2014/07/24/eu-dice-tener-evidencia-de-que-rusia-esta-atacando-a-ucrania",
                    "wgt": 1
                },
                {
                    "body": "El periodista de la agencia de noticias Matthew Lee, conocido por sus enfrentamientos frecuentes con portavoces durante sesiones de informaci\u00f3n del Departamento de Estado de EE.UU., plante\u00f3 varias preguntas acerca de las \u00faltimas afirmaciones del Gobierno de Washington durante la conferencia de prensa que se llev\u00f3 a cabo este jueves.\n\n\"Tenemos nuevas pruebas de que los rusos han tratado de transferir los lanzacohetes m\u00e1s pesados y m\u00e1s potentes a las fuerzas separatistas en Ucrania, y tambi\u00e9n tenemos evidencia de que Rusia est\u00e1 llevando a cabo fuego de artiller\u00eda desde sus territorio para atacar las posiciones militares de Ucrania\", afirm\u00f3 Harf.\n\nNo obstante, cuando Lee le pregunt\u00f3 si pod\u00eda aportar alguna prueba a su declaraci\u00f3n, Harf dijo que el Departamento de Estado no est\u00e1 dispuesto en este momento a revelar m\u00e1s detalles, ya que hacerlo podr\u00eda exponer las operaciones secretas de la inteligencia responsable de las afirmaciones.\n\n\"No puedo profundizar en las fuentes y los m\u00e9todos que est\u00e1n detr\u00e1s de esto. Y no puedo decir en qu\u00e9 est\u00e1 basada la informaci\u00f3n\", insisti\u00f3 Harf.\n\nEntonces el periodista ha se\u00f1alado que las alegaciones formuladas anteriormente por el Departamento de Estado respecto a la relaci\u00f3n de Rusia con la cat\u00e1strofe del MH17 no llegaron a ser consideradas \"pruebas definitivas\".\n\nCuando Lee volvi\u00f3 a cuestionar la decisi\u00f3n del Departamento de Estado de no hacer p\u00fablicas pruebas que apoyen sus afirmaciones, Harf pregunt\u00f3: \"\u00bfPreferir\u00eda que no le diera la informaci\u00f3n solo porque no le puedo revelar la fuente?\"\n\n\"Creo que ser\u00eda mejor para todas las partes interesadas que, cuando usted haga acusaciones como esta, pudiera respaldarla con algo m\u00e1s que con un 'porque yo lo digo'\", respondi\u00f3 Lee.\n\n\"Ustedes se juntan en el Consejo de Seguridad de la ONU para hacer estas acusaciones, el secretario [del Departamento de Estado, John Kerry] hace declaraciones [...] y luego, cuando usted presenta sus pruebas para confirmar esas alegaciones, resulta que les faltan las pruebas definitivas\", continu\u00f3.\n\nAnteriormente, durante una conferencia de inteligencia de EE.UU. altamente publicitada durante la cual se esperaba que los funcionarios estadounidenses presentaran su evaluaci\u00f3n de la cat\u00e1strofe del MH17, los representantes del Gobierno de Washington se vieron obligados a admitir que no hab\u00eda pruebas de que Rusia estuviera implicada en el derribo.",
                    "date": "2014-07-25",
                    "eventUri": "1069645",
                    "id": "16121970",
                    "isDuplicate": false,
                    "lang": "spa",
                    "sim": 0.5512,
                    "source": {
                        "title": "RT en Espa\u00f1ol",
                        "uri": "actualidad.rt.com"
                    },
                    "time": "05:20:00",
                    "title": "EE.UU. acusa sin pruebas a Rusia de fuego de artiller\u00eda contra Ucrania",
                    "uri": "199585318",
                    "url": "http://actualidad.rt.com/actualidad/view/134993-eeuu-rusia-fuego-artilleria-ucrania-evidencias",
                    "wgt": 1
                },
                {
                    "body": "El Comit\u00e9 Interestatal de Aviaci\u00f3n de rusia ha asegurado este viernes que las cajas negras del avi\u00f3n de Malaysia Airlines que se estrell\u00f3 en el este de Ucrania el 17 de julio s\u00f3lo han sufrido ligeros da\u00f1os que no afectan a los datos que contienen.\n\nMOSC\u00da, 25 (Reuters/EP)\n\n\"Durante la inspecci\u00f3n se ha determinado que las grabadoras sufrieron ligeros da\u00f1os mec\u00e1nicos que no afectan a su integridad\", ha explicado en un comunicado esta instituci\u00f3n rusa encargada de supervisar las operaciones a\u00e9reas civiles.\n\nEl Comit\u00e9 ha asegurado que no hay signos de que las cajas negras hayan sido manipuladas, en l\u00ednea similar a declaraciones anteriores de expertos de Pa\u00edses Bajos. Rusia es uno de los pa\u00edses que est\u00e1n participando en el an\u00e1lisis de las cajas negras.",
                    "date": "2014-07-25",
                    "eventUri": "1069645",
                    "id": "16147726",
                    "isDuplicate": false,
                    "lang": "spa",
                    "sim": 0.4884,
                    "source": {
                        "title": "El Economista",
                        "uri": "www.eleconomista.es"
                    },
                    "time": "13:40:00",
                    "title": "Rusia dice que las cajas negras del MH17 s\u00f3lo han sufrido ligeros da\u00f1os que no afectan a los datos",
                    "uri": "199663387",
                    "url": "http://www.eleconomista.es/internacional/noticias/5968631/07/14/Rusia-dice-que-las-cajas-negras-del-MH17-solo-han-sufrido-ligeros-danos-que-no-afectan-a-los-datos.html",
                    "wgt": 1
                }
            ]
        },
        "info": {
            "articleCount": 8,
            "averageDate": "2014-07-25",
            "avgCos": 0.6983,
            "categories": [],
            "customDate": false,
            "customLocation": false,
            "eventUri": "1069645",
            "extractedDate": "",
            "extractedDateEnd": "",
            "id": "1035945",
            "lang": "spa",
            "storyDate": "2014-07-25",
            "storyDateEnd": "",
            "uri": "e7e700df-6a06-44ea-a4f3-f736278fc36b-222287",
            "variance": 0.5124
        }
    },
    "meta": {
        "CCAArticleMatchCount": 35,
        "CCAArticleMatchRatio": 0.2991452991452991,
        "CCAAvgCosSim": 0.78846,
        "CCAAvgMatchWgt": 64.82857142857142,
        "_articleUri1": "199701201",
        "_articleUri2": "199520405",
        "_datetime": "2015-02-19 21:27:42",
        "_ruleBasedShouldMerge": false,
        "_storyUri1": "850f305d-14db-4c75-b547-79470a557ea3-598679",
        "_storyUri2": "e7e700df-6a06-44ea-a4f3-f736278fc36b-222287",
        "_username": "Evgenia Belyaeva",
        "artCount1": 11,
        "artCount2": 8,
        "avgCosSimStory1": 0.557,
        "avgCosSimStory2": 0.6983,
        "categorySim": 0,
        "conceptCosSim": 0.1768073452523568,
        "conceptJaccardSim": 0.09333333333333334,
        "coreTime1": 127672.6666666667,
        "coreTime2": 127652.7,
        "coreTimeStDev1": 2.765540948034181,
        "coreTimeStDev2": 30.22108114644038,
        "entityCosSim": 0.5392281642071103,
        "entityJaccardSim": 0.09375,
        "extractedDateJaccardSim": 0,
        "extractedDatesStory1": 1,
        "extractedDatesStory2": 0,
        "hasSameLocation": 0,
        "keywordCosSim": 0.06920902664993552,
        "keywordJaccardSim": 0.09302325581395349,
        "lang1": "eng",
        "lang2": "spa",
        "matchingDateCount": 0,
        "matchingDateRatio": 0,
        "ratioAnnotatedArticlesStory1": 1,
        "ratioAnnotatedArticlesStory2": 1,
        "shouldMerge": true,
        "storyQuality1": 16,
        "storyQuality2": 13,
        "timeAvg1": 127673.753030303,
        "timeAvg2": 127670.7604166667,
        "timeStDev1": 3.554956833773642,
        "timeStDev2": 30.22108114644038,
        "varianceStory1": 0.1897,
        "varianceStory2": 0.5124
    }
}